Bixpy/__init__.py
Bixpy/helper.py
Bixpy/account/__init__.py
Bixpy/account/_agant.py
Bixpy/account/_fund.py
Bixpy/account/_listen_key.py
Bixpy/account/_sub_account.py
Bixpy/account/_wallet.py
Bixpy/copy_trading/__init__.py
Bixpy/copy_trading/_interface.py
Bixpy/perpetual/__init__.py
Bixpy/perpetual/_account.py
Bixpy/perpetual/_market.py
Bixpy/perpetual/_trade.py
Bixpy/spot/__init__.py
Bixpy/spot/_account.py
Bixpy/spot/_market.py
Bixpy/spot/_trade.py
Bixpy/standard/__init__.py
Bixpy/standard/_interface.py
Bixpy/utils/__init__.py
Bixpy/utils/_endpoints.py
Bixpy/utils/api_client.py
Bixpy/utils/error.py
Bixpy/utils/objects.py
Bixpy/utils/types.py
Bixpy/utils/urls.py
Bixpy/utils/utils.py
Bixpy/utils/ws_client.py
Bixpy/utils/ws_manager.py
bixpy-1.0.3.dist-info/licenses/LICENSE
bixpy-1.0.3.dist-info/METADATA
bixpy-1.0.3.dist-info/WHEEL
bixpy-1.0.3.dist-info/top_level.txt
bixpy-1.0.3.dist-info/RECORD
